README.md
setup.cfg
setup.py
rextester_py/__init__.py
rextester_py/data.py
rextester_py/rextester.py
rextester_py/rextester_aio.py
rextester_py.egg-info/PKG-INFO
rextester_py.egg-info/SOURCES.txt
rextester_py.egg-info/dependency_links.txt
rextester_py.egg-info/not-zip-safe
rextester_py.egg-info/requires.txt
rextester_py.egg-info/top_level.txt