Metadata-Version: 1.1
Name: rextester-py
Version: 0.0.2
Summary: Simple Python interface for rextester.com, using aiohttp/requests
Home-page: https://github.com/nitanmarcel/rextester_py
Author: nitanmarcel
Author-email: nitan.marcel@gmail.com
License: MIT
Platform: any
Classifier: Environment :: Web Environment
Classifier: Intended Audience :: Developers
Classifier: Operating System :: OS Independent
Classifier: Programming Language :: Python
Classifier: Programming Language :: Python :: 3.6
Classifier: Programming Language :: Python :: 3.7
Classifier: Topic :: Internet :: WWW/HTTP :: Dynamic Content
Classifier: Topic :: Software Development :: Libraries :: Python Modules
